aospy/__config__.py
aospy/__init__.py
aospy/_constants.py
aospy/_version.py
aospy/automate.py
aospy/calc.py
aospy/data_loader.py
aospy/internal_names.py
aospy/model.py
aospy/proj.py
aospy/region.py
aospy/run.py
aospy/var.py
aospy/examples/__init__.py
aospy/examples/aospy_main.py
aospy/examples/example_obj_lib.py
aospy/test/__init__.py
aospy/test/test_automate.py
aospy/test/test_calc_basic.py
aospy/test/test_data_loader.py
aospy/test/test_region.py
aospy/test/test_run.py
aospy/test/test_tutorial.py
aospy/test/test_utils_io.py
aospy/test/test_utils_longitude.py
aospy/test/test_utils_times.py
aospy/test/test_utils_vertcoord.py
aospy/test/data/__init__.py
aospy/test/data/netcdf/00040101.precip_monthly.nc
aospy/test/data/netcdf/00050101.precip_monthly.nc
aospy/test/data/netcdf/00060101.precip_monthly.nc
aospy/test/data/netcdf/00060101.sphum_monthly.nc
aospy/test/data/netcdf/im.landmask.nc
aospy/test/data/objects/__init__.py
aospy/test/data/objects/examples.py
aospy/utils/__init__.py
aospy/utils/io.py
aospy/utils/longitude.py
aospy/utils/times.py
aospy/utils/vertcoord.py
aospy-0.3.1.data/scripts/aospy_main.py
aospy-0.3.1.data/scripts/example_obj_lib.py
aospy-0.3.1.dist-info/DESCRIPTION.rst
aospy-0.3.1.dist-info/METADATA
aospy-0.3.1.dist-info/RECORD
aospy-0.3.1.dist-info/WHEEL
aospy-0.3.1.dist-info/metadata.json
aospy-0.3.1.dist-info/top_level.txt
