Metadata-Version: 2.0
Name: aospy
Version: 0.3.1
Summary: Automated gridded climate data analysis and management
Home-page: https://github.com/spencerahill/aospy
Author: aospy Developers
Author-email: aospy@googlegroups.com
License: Apache
Keywords: climate science netcdf xarray
Platform: UNKNOWN
Classifier: Development Status :: 4 - Beta
Classifier: Intended Audience :: Science/Research
Classifier: License :: OSI Approved :: Apache Software License
Classifier: Natural Language :: English
Classifier: Operating System :: OS Independent
Classifier: Programming Language :: Python :: 3
Classifier: Programming Language :: Python :: 3.5
Classifier: Programming Language :: Python :: 3.6
Classifier: Programming Language :: Python :: 3.7
Classifier: Topic :: Scientific/Engineering :: Atmospheric Science
Requires-Dist: cftime (>=1.0.0)
Requires-Dist: cloudpickle (>=0.2.1)
Requires-Dist: dask (>=0.14)
Requires-Dist: distributed (>=1.17.1)
Requires-Dist: netCDF4 (>=1.2)
Requires-Dist: numpy (>=1.7)
Requires-Dist: pandas (>=0.15.0)
Requires-Dist: scipy (>=0.16)
Requires-Dist: toolz (>=0.7.2)
Requires-Dist: xarray (>=0.10.6)
